{"DCl2Il9n+co7GRFDmc4dBw==":"shutterstock-368660738-1000x667.png","/as48QWvgmEXrahxdct0BA==":"lory-blanco-129x128.png","1zR+bKAxmxpSqy270wwZQw==":"propuesta-2000x1334.png","0x9QfzmCxaq+ETTAccTdhw==":"shutterstock-265942184-1000x667.png","6Er0Aq3q+KabhNBlgSS98w==":"field-footwear-grass-186035-2000x1333.jpg","LYDBXq+pkc5Zt+sRJrVT0A==":"brand-design-fashion-1598508-2000x1333.jpg","9rLFz8JJJ6lb+VEDKqIgPQ==":"blue-boots-classic-266840-2000x1500.jpg","96lVoppGtZtcBlJq4axv+g==":"shutterstock-1186150135-1000x667.png","+x6I1YwrWljtAtIy4UUsyA==":"blue-casual-colors-292999-2000x1325.jpg","iCpdyJUJIsJQUSaLlpptQw==":"mesa%20de%20trabajo%2022-8-265x102.png","grM33qWETMoWgUC5L+OpGA==":"mesa%20de%20trabajo%2022-8-128x49.png","ULNEnYIMMGYalDysiSftLA==":"mesa%20de%20trabajo%2023-8-128x127.png","t8jYjmseS8M2zagADYnO0Q==":"mesa%20de%20trabajo%2023-8-129x128.png","w1s4zcZBwLLwenpbtB7kDg==":"portada-lory-1000x667.png","IHHHu/MtVbYslFkxSkUzYA==":"portada-lory-1-1000x667.png","fgqnszh5O/G7D/NurOTmtw==":"portada-lory-2-1000x667.png","KZmXZored1q4EhmcVPYhqA==":"portada-lory-3-1000x667.png","vnUb2s/w0O8LlhZny9/mAQ==":"portlory-1000x667.png","fOcgBdbYqBunrMH10mgbmA==":"mesa%20de%20trabajo%202%20copia-8-1001x668.png","wDgolMlWCc0x/SX0M6R5PQ==":"mesa%20de%20trabajo%202%20copia-8-1001x668.png","FBYb/+CtrT6fWzfoRclXFw==":"prtada%20lory%20web-8-1493x995.png"}